{
 "/home/vlad/facultate/licenta/app/src/App.tsx": {
  "ORBGjAfxVOUrSWy": {
   "type": "view",
   "meta": {
    "name": "App",
    "location": {
     "start": {
      "line": 17,
      "column": 13
     },
     "end": {
      "line": 39,
      "column": 1
     }
    },
    "absoluteFilePath": "/home/vlad/facultate/licenta/app/src/App.tsx",
    "absoluteRootPath": "/home/vlad/facultate/licenta/app",
    "relativeFilePath": "src/App.tsx"
   },
   "sourceId": "/home/vlad/facultate/licenta/app/src/App.tsx:App",
   "buildId": "ORBGjAfxVOUrSWy",
   "params": {
    "type": "STRUCT",
    "value": {
     "isStateInitiated": {
      "type": "OBSERVE",
      "path": [
       {
        "type": "CONST",
        "value": "isStateInitiated"
       }
      ]
     }
    }
   }
  }
 },
 "/home/vlad/facultate/licenta/app/src/components/helpers/loader.tsx": {
  "kwcPgojRNAZtAZf": {
   "type": "view",
   "meta": {
    "name": "Loader",
    "location": {
     "start": {
      "line": 4,
      "column": 13
     },
     "end": {
      "line": 11,
      "column": 1
     }
    },
    "absoluteFilePath": "/home/vlad/facultate/licenta/app/src/components/helpers/loader.tsx",
    "absoluteRootPath": "/home/vlad/facultate/licenta/app",
    "relativeFilePath": "src/components/helpers/loader.tsx"
   },
   "sourceId": "/home/vlad/facultate/licenta/app/src/components/helpers/loader.tsx:Loader",
   "buildId": "kwcPgojRNAZtAZf",
   "params": {
    "type": "PASSTHROUGH"
   }
  }
 },
 "/home/vlad/facultate/licenta/app/src/components/navbar/index.tsx": {
  "BSJIeCeEitvfKba": {
   "type": "view",
   "meta": {
    "name": "NavBar",
    "location": {
     "start": {
      "line": 20,
      "column": 13
     },
     "end": {
      "line": 303,
      "column": 1
     }
    },
    "absoluteFilePath": "/home/vlad/facultate/licenta/app/src/components/navbar/index.tsx",
    "absoluteRootPath": "/home/vlad/facultate/licenta/app",
    "relativeFilePath": "src/components/navbar/index.tsx"
   },
   "sourceId": "/home/vlad/facultate/licenta/app/src/components/navbar/index.tsx:NavBar",
   "buildId": "BSJIeCeEitvfKba",
   "params": {
    "type": "STRUCT",
    "value": {
     "user": {
      "type": "OBSERVE",
      "path": [
       {
        "type": "CONST",
        "value": "user"
       }
      ]
     },
     "updateIsLogoutPressed": {
      "type": "UPDATE",
      "path": [
       {
        "type": "CONST",
        "value": "isLogoutPressed"
       }
      ]
     }
    }
   }
  }
 },
 "/home/vlad/facultate/licenta/app/src/views/home/index.tsx": {
  "_zOqYMammsVbFoZ": {
   "type": "view",
   "meta": {
    "name": "Home",
    "location": {
     "start": {
      "line": 5,
      "column": 13
     },
     "end": {
      "line": 9,
      "column": 1
     }
    },
    "absoluteFilePath": "/home/vlad/facultate/licenta/app/src/views/home/index.tsx",
    "absoluteRootPath": "/home/vlad/facultate/licenta/app",
    "relativeFilePath": "src/views/home/index.tsx"
   },
   "sourceId": "/home/vlad/facultate/licenta/app/src/views/home/index.tsx:Home",
   "buildId": "_zOqYMammsVbFoZ",
   "params": {
    "type": "PASSTHROUGH"
   }
  }
 },
 "/home/vlad/facultate/licenta/app/src/views/schedule/index.tsx": {
  "OmUqQUmejLJDnGu": {
   "type": "view",
   "meta": {
    "name": "Schedule",
    "location": {
     "start": {
      "line": 10,
      "column": 13
     },
     "end": {
      "line": 129,
      "column": 1
     }
    },
    "absoluteFilePath": "/home/vlad/facultate/licenta/app/src/views/schedule/index.tsx",
    "absoluteRootPath": "/home/vlad/facultate/licenta/app",
    "relativeFilePath": "src/views/schedule/index.tsx"
   },
   "sourceId": "/home/vlad/facultate/licenta/app/src/views/schedule/index.tsx:Schedule",
   "buildId": "OmUqQUmejLJDnGu",
   "params": {
    "type": "STRUCT",
    "value": {
     "user": {
      "type": "OBSERVE",
      "path": [
       {
        "type": "CONST",
        "value": "user"
       }
      ]
     },
     "getClasses": {
      "type": "GET",
      "path": [
       {
        "type": "CONST",
        "value": "classes"
       }
      ]
     },
     "getStudents": {
      "type": "GET",
      "path": [
       {
        "type": "CONST",
        "value": "students"
       }
      ]
     },
     "getParents": {
      "type": "GET",
      "path": [
       {
        "type": "CONST",
        "value": "parents"
       }
      ]
     },
     "getUsers": {
      "type": "GET",
      "path": [
       {
        "type": "CONST",
        "value": "users"
       }
      ]
     },
     "schedules": {
      "type": "OBSERVE",
      "path": [
       {
        "type": "CONST",
        "value": "schedules"
       }
      ]
     },
     "updateScheduleClass": {
      "type": "UPDATE",
      "path": [
       {
        "type": "CONST",
        "value": "schedule"
       },
       {
        "type": "CONST",
        "value": "class"
       }
      ]
     },
     "updateSchedule": {
      "type": "UPDATE",
      "path": [
       {
        "type": "CONST",
        "value": "schedule"
       },
       {
        "type": "CONST",
        "value": "schedule"
       }
      ]
     },
     "updateScheduleStudent": {
      "type": "UPDATE",
      "path": [
       {
        "type": "CONST",
        "value": "schedule"
       },
       {
        "type": "CONST",
        "value": "student"
       }
      ]
     },
     "isStateInitiated": {
      "type": "OBSERVE",
      "path": [
       {
        "type": "CONST",
        "value": "schedule"
       },
       {
        "type": "CONST",
        "value": "isStateInitiated"
       }
      ]
     }
    }
   }
  }
 },
 "/home/vlad/facultate/licenta/app/src/views/general/index.tsx": {
  "EuxisDvYOWiSANS": {
   "type": "view",
   "meta": {
    "name": "General",
    "location": {
     "start": {
      "line": 15,
      "column": 13
     },
     "end": {
      "line": 172,
      "column": 1
     }
    },
    "absoluteFilePath": "/home/vlad/facultate/licenta/app/src/views/general/index.tsx",
    "absoluteRootPath": "/home/vlad/facultate/licenta/app",
    "relativeFilePath": "src/views/general/index.tsx"
   },
   "sourceId": "/home/vlad/facultate/licenta/app/src/views/general/index.tsx:General",
   "buildId": "EuxisDvYOWiSANS",
   "params": {
    "type": "STRUCT",
    "value": {
     "updateModalFormData": {
      "type": "UPDATE",
      "path": [
       {
        "type": "CONST",
        "value": "modal"
       },
       {
        "type": "CONST",
        "value": "formData"
       }
      ]
     },
     "isModalSavePressed": {
      "type": "OBSERVE",
      "path": [
       {
        "type": "CONST",
        "value": "modal"
       },
       {
        "type": "CONST",
        "value": "isSavePressed"
       }
      ]
     },
     "updateIsModalSavePressed": {
      "type": "UPDATE",
      "path": [
       {
        "type": "CONST",
        "value": "modal"
       },
       {
        "type": "CONST",
        "value": "isSavePressed"
       }
      ]
     },
     "updateIsModalOpen": {
      "type": "UPDATE",
      "path": [
       {
        "type": "CONST",
        "value": "modal"
       },
       {
        "type": "CONST",
        "value": "isOpen"
       }
      ]
     },
     "getModalFormData": {
      "type": "GET",
      "path": [
       {
        "type": "CONST",
        "value": "modal"
       },
       {
        "type": "CONST",
        "value": "formData"
       }
      ]
     },
     "messages": {
      "type": "OBSERVE",
      "path": [
       {
        "type": "CONST",
        "value": "messages"
       },
       {
        "type": "CONST",
        "value": "content"
       }
      ]
     },
     "updateMessages": {
      "type": "UPDATE",
      "path": [
       {
        "type": "CONST",
        "value": "messages"
       },
       {
        "type": "CONST",
        "value": "content"
       }
      ]
     },
     "getUser": {
      "type": "GET",
      "path": [
       {
        "type": "CONST",
        "value": "user"
       }
      ]
     },
     "getUsers": {
      "type": "GET",
      "path": [
       {
        "type": "CONST",
        "value": "users"
       }
      ]
     }
    }
   }
  }
 },
 "/home/vlad/facultate/licenta/app/src/views/catalogue/index.tsx": {
  "LLAfAhJ_TuoFQmt": {
   "type": "view",
   "meta": {
    "name": "Catalogue",
    "location": {
     "start": {
      "line": 10,
      "column": 13
     },
     "end": {
      "line": 157,
      "column": 1
     }
    },
    "absoluteFilePath": "/home/vlad/facultate/licenta/app/src/views/catalogue/index.tsx",
    "absoluteRootPath": "/home/vlad/facultate/licenta/app",
    "relativeFilePath": "src/views/catalogue/index.tsx"
   },
   "sourceId": "/home/vlad/facultate/licenta/app/src/views/catalogue/index.tsx:Catalogue",
   "buildId": "LLAfAhJ_TuoFQmt",
   "params": {
    "type": "STRUCT",
    "value": {
     "user": {
      "type": "OBSERVE",
      "path": [
       {
        "type": "CONST",
        "value": "user"
       }
      ]
     },
     "getClasses": {
      "type": "GET",
      "path": [
       {
        "type": "CONST",
        "value": "classes"
       }
      ]
     },
     "getTeachers": {
      "type": "GET",
      "path": [
       {
        "type": "CONST",
        "value": "teachers"
       }
      ]
     },
     "getStudents": {
      "type": "GET",
      "path": [
       {
        "type": "CONST",
        "value": "students"
       }
      ]
     },
     "getParents": {
      "type": "GET",
      "path": [
       {
        "type": "CONST",
        "value": "parents"
       }
      ]
     },
     "getUsers": {
      "type": "GET",
      "path": [
       {
        "type": "CONST",
        "value": "users"
       }
      ]
     },
     "updateCatalogueTeacher": {
      "type": "UPDATE",
      "path": [
       {
        "type": "CONST",
        "value": "catalogue"
       },
       {
        "type": "CONST",
        "value": "teacher"
       }
      ]
     },
     "updateCatalogueClass": {
      "type": "UPDATE",
      "path": [
       {
        "type": "CONST",
        "value": "catalogue"
       },
       {
        "type": "CONST",
        "value": "class"
       }
      ]
     },
     "catalogueClass": {
      "type": "OBSERVE",
      "path": [
       {
        "type": "CONST",
        "value": "catalogue"
       },
       {
        "type": "CONST",
        "value": "class"
       }
      ]
     },
     "updateCatalogueStudent": {
      "type": "UPDATE",
      "path": [
       {
        "type": "CONST",
        "value": "catalogue"
       },
       {
        "type": "CONST",
        "value": "student"
       }
      ]
     }
    }
   }
  }
 },
 "/home/vlad/facultate/licenta/app/src/views/teme/index.tsx": {
  "nYWvxvjPEbExLXm": {
   "type": "view",
   "meta": {
    "name": "Teme",
    "location": {
     "start": {
      "line": 5,
      "column": 13
     },
     "end": {
      "line": 9,
      "column": 1
     }
    },
    "absoluteFilePath": "/home/vlad/facultate/licenta/app/src/views/teme/index.tsx",
    "absoluteRootPath": "/home/vlad/facultate/licenta/app",
    "relativeFilePath": "src/views/teme/index.tsx"
   },
   "sourceId": "/home/vlad/facultate/licenta/app/src/views/teme/index.tsx:Teme",
   "buildId": "nYWvxvjPEbExLXm",
   "params": {
    "type": "PASSTHROUGH"
   }
  }
 },
 "/home/vlad/facultate/licenta/app/src/views/requests/index.tsx": {
  "gUkXOPMPkPuLeKs": {
   "type": "view",
   "meta": {
    "name": "Requests",
    "location": {
     "start": {
      "line": 10,
      "column": 13
     },
     "end": {
      "line": 21,
      "column": 1
     }
    },
    "absoluteFilePath": "/home/vlad/facultate/licenta/app/src/views/requests/index.tsx",
    "absoluteRootPath": "/home/vlad/facultate/licenta/app",
    "relativeFilePath": "src/views/requests/index.tsx"
   },
   "sourceId": "/home/vlad/facultate/licenta/app/src/views/requests/index.tsx:Requests",
   "buildId": "gUkXOPMPkPuLeKs",
   "params": {
    "type": "STRUCT",
    "value": {
     "user": {
      "type": "OBSERVE",
      "path": [
       {
        "type": "CONST",
        "value": "user"
       }
      ]
     }
    }
   }
  }
 },
 "/home/vlad/facultate/licenta/app/src/views/login/index.tsx": {
  "qZyTeayQhueFbrP": {
   "type": "view",
   "meta": {
    "name": "Login",
    "location": {
     "start": {
      "line": 8,
      "column": 13
     },
     "end": {
      "line": 79,
      "column": 1
     }
    },
    "absoluteFilePath": "/home/vlad/facultate/licenta/app/src/views/login/index.tsx",
    "absoluteRootPath": "/home/vlad/facultate/licenta/app",
    "relativeFilePath": "src/views/login/index.tsx"
   },
   "sourceId": "/home/vlad/facultate/licenta/app/src/views/login/index.tsx:Login",
   "buildId": "qZyTeayQhueFbrP",
   "params": {
    "type": "STRUCT",
    "value": {
     "updateUser": {
      "type": "UPDATE",
      "path": [
       {
        "type": "CONST",
        "value": "user"
       }
      ]
     }
    }
   }
  }
 },
 "/home/vlad/facultate/licenta/app/src/producers/initState.ts": {
  "lDyRZSsJZdeZjiT": {
   "type": "producer",
   "meta": {
    "name": "initState",
    "location": {
     "start": {
      "line": 3,
      "column": 13
     },
     "end": {
      "line": 94,
      "column": 1
     }
    },
    "absoluteFilePath": "/home/vlad/facultate/licenta/app/src/producers/initState.ts",
    "absoluteRootPath": "/home/vlad/facultate/licenta/app",
    "relativeFilePath": "src/producers/initState.ts"
   },
   "sourceId": "/home/vlad/facultate/licenta/app/src/producers/initState.ts:initState",
   "buildId": "lDyRZSsJZdeZjiT",
   "params": {
    "type": "STRUCT",
    "value": {
     "updateUser": {
      "type": "UPDATE",
      "path": [
       {
        "type": "CONST",
        "value": "user"
       }
      ]
     },
     "updateTeachers": {
      "type": "UPDATE",
      "path": [
       {
        "type": "CONST",
        "value": "teachers"
       }
      ]
     },
     "updateSubjects": {
      "type": "UPDATE",
      "path": [
       {
        "type": "CONST",
        "value": "subjects"
       }
      ]
     },
     "updateClasses": {
      "type": "UPDATE",
      "path": [
       {
        "type": "CONST",
        "value": "classes"
       }
      ]
     },
     "updateSchedules": {
      "type": "UPDATE",
      "path": [
       {
        "type": "CONST",
        "value": "schedules"
       }
      ]
     },
     "updateUsers": {
      "type": "UPDATE",
      "path": [
       {
        "type": "CONST",
        "value": "users"
       }
      ]
     },
     "updateStudents": {
      "type": "UPDATE",
      "path": [
       {
        "type": "CONST",
        "value": "students"
       }
      ]
     },
     "updateParents": {
      "type": "UPDATE",
      "path": [
       {
        "type": "CONST",
        "value": "parents"
       }
      ]
     },
     "updateIsStateInitiated": {
      "type": "UPDATE",
      "path": [
       {
        "type": "CONST",
        "value": "isStateInitiated"
       }
      ]
     }
    }
   }
  }
 },
 "/home/vlad/facultate/licenta/app/src/producers/logout.ts": {
  "BuSGvodpQWLRvgr": {
   "type": "producer",
   "meta": {
    "name": "Logout",
    "location": {
     "start": {
      "line": 1,
      "column": 13
     },
     "end": {
      "line": 12,
      "column": 1
     }
    },
    "absoluteFilePath": "/home/vlad/facultate/licenta/app/src/producers/logout.ts",
    "absoluteRootPath": "/home/vlad/facultate/licenta/app",
    "relativeFilePath": "src/producers/logout.ts"
   },
   "sourceId": "/home/vlad/facultate/licenta/app/src/producers/logout.ts:Logout",
   "buildId": "BuSGvodpQWLRvgr",
   "params": {
    "type": "STRUCT",
    "value": {
     "isLogoutPressed": {
      "type": "OBSERVE",
      "path": [
       {
        "type": "CONST",
        "value": "isLogoutPressed"
       }
      ]
     },
     "updateIsLogoutPressed": {
      "type": "UPDATE",
      "path": [
       {
        "type": "CONST",
        "value": "isLogoutPressed"
       }
      ]
     },
     "updateUser": {
      "type": "UPDATE",
      "path": [
       {
        "type": "CONST",
        "value": "user"
       }
      ]
     }
    }
   }
  }
 },
 "/home/vlad/facultate/licenta/app/src/views/schedule/table.tsx": {
  "orCHISNayXNKVVQ": {
   "type": "view",
   "meta": {
    "name": "Table",
    "location": {
     "start": {
      "line": 24,
      "column": 13
     },
     "end": {
      "line": 326,
      "column": 1
     }
    },
    "absoluteFilePath": "/home/vlad/facultate/licenta/app/src/views/schedule/table.tsx",
    "absoluteRootPath": "/home/vlad/facultate/licenta/app",
    "relativeFilePath": "src/views/schedule/table.tsx"
   },
   "sourceId": "/home/vlad/facultate/licenta/app/src/views/schedule/table.tsx:Table",
   "buildId": "orCHISNayXNKVVQ",
   "params": {
    "type": "STRUCT",
    "value": {
     "scheduleClass": {
      "type": "OBSERVE",
      "path": [
       {
        "type": "CONST",
        "value": "schedule"
       },
       {
        "type": "CONST",
        "value": "class"
       }
      ]
     },
     "schedule": {
      "type": "OBSERVE",
      "path": [
       {
        "type": "CONST",
        "value": "schedule"
       },
       {
        "type": "CONST",
        "value": "schedule"
       }
      ]
     },
     "scheduleTeacher": {
      "type": "OBSERVE",
      "path": [
       {
        "type": "CONST",
        "value": "schedule"
       },
       {
        "type": "CONST",
        "value": "teacher"
       }
      ]
     },
     "getSchedules": {
      "type": "GET",
      "path": [
       {
        "type": "CONST",
        "value": "schedules"
       }
      ]
     },
     "updateModalFormData": {
      "type": "UPDATE",
      "path": [
       {
        "type": "CONST",
        "value": "modal"
       },
       {
        "type": "CONST",
        "value": "formData"
       }
      ]
     },
     "getTeachersState": {
      "type": "GET",
      "path": [
       {
        "type": "CONST",
        "value": "teachers"
       }
      ]
     },
     "getSubjectsState": {
      "type": "GET",
      "path": [
       {
        "type": "CONST",
        "value": "subjects"
       }
      ]
     },
     "getUsers": {
      "type": "GET",
      "path": [
       {
        "type": "CONST",
        "value": "users"
       }
      ]
     },
     "getUser": {
      "type": "GET",
      "path": [
       {
        "type": "CONST",
        "value": "user"
       }
      ]
     },
     "getClassesState": {
      "type": "GET",
      "path": [
       {
        "type": "CONST",
        "value": "classes"
       }
      ]
     },
     "getScheduleStudent": {
      "type": "GET",
      "path": [
       {
        "type": "CONST",
        "value": "schedule"
       },
       {
        "type": "CONST",
        "value": "student"
       }
      ]
     },
     "updateIsModalOpen": {
      "type": "UPDATE",
      "path": [
       {
        "type": "CONST",
        "value": "modal"
       },
       {
        "type": "CONST",
        "value": "isOpen"
       }
      ]
     }
    }
   }
  }
 },
 "/home/vlad/facultate/licenta/app/src/views/catalogue/table.tsx": {
  "blYvVQXGAlAUgWy": {
   "type": "view",
   "meta": {
    "name": "Table",
    "location": {
     "start": {
      "line": 52,
      "column": 13
     },
     "end": {
      "line": 344,
      "column": 1
     }
    },
    "absoluteFilePath": "/home/vlad/facultate/licenta/app/src/views/catalogue/table.tsx",
    "absoluteRootPath": "/home/vlad/facultate/licenta/app",
    "relativeFilePath": "src/views/catalogue/table.tsx"
   },
   "sourceId": "/home/vlad/facultate/licenta/app/src/views/catalogue/table.tsx:Table",
   "buildId": "blYvVQXGAlAUgWy",
   "params": {
    "type": "STRUCT",
    "value": {
     "catalogueClass": {
      "type": "OBSERVE",
      "path": [
       {
        "type": "CONST",
        "value": "catalogue"
       },
       {
        "type": "CONST",
        "value": "class"
       }
      ]
     },
     "catalogue": {
      "type": "OBSERVE",
      "path": [
       {
        "type": "CONST",
        "value": "catalogue"
       },
       {
        "type": "CONST",
        "value": "catalogue"
       }
      ]
     },
     "updateCatalogue": {
      "type": "UPDATE",
      "path": [
       {
        "type": "CONST",
        "value": "catalogue"
       },
       {
        "type": "CONST",
        "value": "catalogue"
       }
      ]
     },
     "updateModalFormData": {
      "type": "UPDATE",
      "path": [
       {
        "type": "CONST",
        "value": "modal"
       },
       {
        "type": "CONST",
        "value": "formData"
       }
      ]
     },
     "isModalSavePressed": {
      "type": "OBSERVE",
      "path": [
       {
        "type": "CONST",
        "value": "modal"
       },
       {
        "type": "CONST",
        "value": "isSavePressed"
       }
      ]
     },
     "updateIsModalSavePressed": {
      "type": "UPDATE",
      "path": [
       {
        "type": "CONST",
        "value": "modal"
       },
       {
        "type": "CONST",
        "value": "isSavePressed"
       }
      ]
     },
     "updateIsModalOpen": {
      "type": "UPDATE",
      "path": [
       {
        "type": "CONST",
        "value": "modal"
       },
       {
        "type": "CONST",
        "value": "isOpen"
       }
      ]
     },
     "getModalFormData": {
      "type": "GET",
      "path": [
       {
        "type": "CONST",
        "value": "modal"
       },
       {
        "type": "CONST",
        "value": "formData"
       }
      ]
     },
     "getCatalogueTeacher": {
      "type": "GET",
      "path": [
       {
        "type": "CONST",
        "value": "catalogue"
       },
       {
        "type": "CONST",
        "value": "teacher"
       }
      ]
     },
     "getCatalogueStudent": {
      "type": "GET",
      "path": [
       {
        "type": "CONST",
        "value": "catalogue"
       },
       {
        "type": "CONST",
        "value": "student"
       }
      ]
     },
     "getUser": {
      "type": "GET",
      "path": [
       {
        "type": "CONST",
        "value": "user"
       }
      ]
     },
     "getUsers": {
      "type": "GET",
      "path": [
       {
        "type": "CONST",
        "value": "users"
       }
      ]
     },
     "getSubjectsState": {
      "type": "GET",
      "path": [
       {
        "type": "CONST",
        "value": "subjects"
       }
      ]
     }
    }
   }
  }
 },
 "/home/vlad/facultate/licenta/app/src/views/requests/userRequests.tsx": {
  "x_QXIBDsCnj_Dts": {
   "type": "view",
   "meta": {
    "name": "UserRequests",
    "location": {
     "start": {
      "line": 10,
      "column": 13
     },
     "end": {
      "line": 194,
      "column": 1
     }
    },
    "absoluteFilePath": "/home/vlad/facultate/licenta/app/src/views/requests/userRequests.tsx",
    "absoluteRootPath": "/home/vlad/facultate/licenta/app",
    "relativeFilePath": "src/views/requests/userRequests.tsx"
   },
   "sourceId": "/home/vlad/facultate/licenta/app/src/views/requests/userRequests.tsx:UserRequests",
   "buildId": "x_QXIBDsCnj_Dts",
   "params": {
    "type": "STRUCT",
    "value": {
     "user": {
      "type": "OBSERVE",
      "path": [
       {
        "type": "CONST",
        "value": "user"
       }
      ]
     },
     "updateModalFormData": {
      "type": "UPDATE",
      "path": [
       {
        "type": "CONST",
        "value": "modal"
       },
       {
        "type": "CONST",
        "value": "formData"
       }
      ]
     },
     "updateIsModalOpen": {
      "type": "UPDATE",
      "path": [
       {
        "type": "CONST",
        "value": "modal"
       },
       {
        "type": "CONST",
        "value": "isOpen"
       }
      ]
     },
     "requests": {
      "type": "OBSERVE",
      "path": [
       {
        "type": "CONST",
        "value": "requests"
       },
       {
        "type": "CONST",
        "value": "content"
       }
      ]
     },
     "getUsers": {
      "type": "GET",
      "path": [
       {
        "type": "CONST",
        "value": "users"
       }
      ]
     }
    }
   }
  }
 },
 "/home/vlad/facultate/licenta/app/src/views/requests/directorRequests.tsx": {
  "WyxciGXCvXXaoQg": {
   "type": "view",
   "meta": {
    "name": "DirectorRequests",
    "location": {
     "start": {
      "line": 10,
      "column": 13
     },
     "end": {
      "line": 361,
      "column": 1
     }
    },
    "absoluteFilePath": "/home/vlad/facultate/licenta/app/src/views/requests/directorRequests.tsx",
    "absoluteRootPath": "/home/vlad/facultate/licenta/app",
    "relativeFilePath": "src/views/requests/directorRequests.tsx"
   },
   "sourceId": "/home/vlad/facultate/licenta/app/src/views/requests/directorRequests.tsx:DirectorRequests",
   "buildId": "WyxciGXCvXXaoQg",
   "params": {
    "type": "STRUCT",
    "value": {
     "user": {
      "type": "OBSERVE",
      "path": [
       {
        "type": "CONST",
        "value": "user"
       }
      ]
     },
     "updateModalFormData": {
      "type": "UPDATE",
      "path": [
       {
        "type": "CONST",
        "value": "modal"
       },
       {
        "type": "CONST",
        "value": "formData"
       }
      ]
     },
     "updateIsModalOpen": {
      "type": "UPDATE",
      "path": [
       {
        "type": "CONST",
        "value": "modal"
       },
       {
        "type": "CONST",
        "value": "isOpen"
       }
      ]
     },
     "requests": {
      "type": "OBSERVE",
      "path": [
       {
        "type": "CONST",
        "value": "requests"
       },
       {
        "type": "CONST",
        "value": "content"
       }
      ]
     },
     "getStudents": {
      "type": "GET",
      "path": [
       {
        "type": "CONST",
        "value": "students"
       }
      ]
     },
     "getUsers": {
      "type": "GET",
      "path": [
       {
        "type": "CONST",
        "value": "users"
       }
      ]
     }
    }
   }
  }
 },
 "/home/vlad/facultate/licenta/app/src/components/modals/modalForm/index.tsx": {
  "aGherqORFDJRDVf": {
   "type": "view",
   "meta": {
    "name": "Modal",
    "location": {
     "start": {
      "line": 7,
      "column": 13
     },
     "end": {
      "line": 77,
      "column": 1
     }
    },
    "absoluteFilePath": "/home/vlad/facultate/licenta/app/src/components/modals/modalForm/index.tsx",
    "absoluteRootPath": "/home/vlad/facultate/licenta/app",
    "relativeFilePath": "src/components/modals/modalForm/index.tsx"
   },
   "sourceId": "/home/vlad/facultate/licenta/app/src/components/modals/modalForm/index.tsx:Modal",
   "buildId": "aGherqORFDJRDVf",
   "params": {
    "type": "STRUCT",
    "value": {
     "title": {
      "type": "VALUE",
      "value": {
       "type": "EXTERNAL",
       "path": [
        "title"
       ]
      }
     },
     "fields": {
      "type": "VALUE",
      "value": {
       "type": "EXTERNAL",
       "path": [
        "fields"
       ]
      }
     },
     "type": {
      "type": "VALUE",
      "value": {
       "type": "EXTERNAL",
       "path": [
        "type"
       ]
      }
     },
     "updateIsModalSavePressed": {
      "type": "UPDATE",
      "path": [
       {
        "type": "CONST",
        "value": "modal"
       },
       {
        "type": "CONST",
        "value": "isSavePressed"
       }
      ]
     },
     "updateModalFormData": {
      "type": "UPDATE",
      "path": [
       {
        "type": "CONST",
        "value": "modal"
       },
       {
        "type": "CONST",
        "value": "formData"
       }
      ]
     },
     "updateIsModalOpen": {
      "type": "UPDATE",
      "path": [
       {
        "type": "CONST",
        "value": "modal"
       },
       {
        "type": "CONST",
        "value": "isOpen"
       }
      ]
     }
    }
   }
  }
 },
 "/home/vlad/facultate/licenta/app/src/views/schedule/producers/initState.ts": {
  "cIglBUglkEPHdTk": {
   "type": "producer",
   "meta": {
    "name": "initState",
    "location": {
     "start": {
      "line": 3,
      "column": 13
     },
     "end": {
      "line": 50,
      "column": 1
     }
    },
    "absoluteFilePath": "/home/vlad/facultate/licenta/app/src/views/schedule/producers/initState.ts",
    "absoluteRootPath": "/home/vlad/facultate/licenta/app",
    "relativeFilePath": "src/views/schedule/producers/initState.ts"
   },
   "sourceId": "/home/vlad/facultate/licenta/app/src/views/schedule/producers/initState.ts:initState",
   "buildId": "cIglBUglkEPHdTk",
   "params": {
    "type": "STRUCT",
    "value": {
     "updateSchedules": {
      "type": "UPDATE",
      "path": [
       {
        "type": "CONST",
        "value": "schedules"
       }
      ]
     },
     "updateIsStateInitiated": {
      "type": "UPDATE",
      "path": [
       {
        "type": "CONST",
        "value": "schedule"
       },
       {
        "type": "CONST",
        "value": "isStateInitiated"
       }
      ]
     },
     "updateScheduleTeacher": {
      "type": "UPDATE",
      "path": [
       {
        "type": "CONST",
        "value": "schedule"
       },
       {
        "type": "CONST",
        "value": "teacher"
       }
      ]
     },
     "user": {
      "type": "OBSERVE",
      "path": [
       {
        "type": "CONST",
        "value": "user"
       }
      ]
     },
     "getTeachersState": {
      "type": "GET",
      "path": [
       {
        "type": "CONST",
        "value": "teachers"
       }
      ]
     }
    }
   }
  }
 },
 "/home/vlad/facultate/licenta/app/src/views/schedule/producers/modalSaved.ts": {
  "UdhgrHeGWJBjJzD": {
   "type": "producer",
   "meta": {
    "name": "modalSaved",
    "location": {
     "start": {
      "line": 22,
      "column": 13
     },
     "end": {
      "line": 148,
      "column": 1
     }
    },
    "absoluteFilePath": "/home/vlad/facultate/licenta/app/src/views/schedule/producers/modalSaved.ts",
    "absoluteRootPath": "/home/vlad/facultate/licenta/app",
    "relativeFilePath": "src/views/schedule/producers/modalSaved.ts"
   },
   "sourceId": "/home/vlad/facultate/licenta/app/src/views/schedule/producers/modalSaved.ts:modalSaved",
   "buildId": "UdhgrHeGWJBjJzD",
   "params": {
    "type": "STRUCT",
    "value": {
     "scheduleClass": {
      "type": "OBSERVE",
      "path": [
       {
        "type": "CONST",
        "value": "schedule"
       },
       {
        "type": "CONST",
        "value": "class"
       }
      ]
     },
     "schedule": {
      "type": "OBSERVE",
      "path": [
       {
        "type": "CONST",
        "value": "schedule"
       },
       {
        "type": "CONST",
        "value": "schedule"
       }
      ]
     },
     "updateSchedule": {
      "type": "UPDATE",
      "path": [
       {
        "type": "CONST",
        "value": "schedule"
       },
       {
        "type": "CONST",
        "value": "schedule"
       }
      ]
     },
     "updateSchedules": {
      "type": "UPDATE",
      "path": [
       {
        "type": "CONST",
        "value": "schedules"
       }
      ]
     },
     "getSchedules": {
      "type": "GET",
      "path": [
       {
        "type": "CONST",
        "value": "schedules"
       }
      ]
     },
     "updateModalFormData": {
      "type": "UPDATE",
      "path": [
       {
        "type": "CONST",
        "value": "modal"
       },
       {
        "type": "CONST",
        "value": "formData"
       }
      ]
     },
     "isModalSavePressed": {
      "type": "OBSERVE",
      "path": [
       {
        "type": "CONST",
        "value": "modal"
       },
       {
        "type": "CONST",
        "value": "isSavePressed"
       }
      ]
     },
     "updateIsModalSavePressed": {
      "type": "UPDATE",
      "path": [
       {
        "type": "CONST",
        "value": "modal"
       },
       {
        "type": "CONST",
        "value": "isSavePressed"
       }
      ]
     },
     "getModalFormData": {
      "type": "GET",
      "path": [
       {
        "type": "CONST",
        "value": "modal"
       },
       {
        "type": "CONST",
        "value": "formData"
       }
      ]
     },
     "getTeachersState": {
      "type": "GET",
      "path": [
       {
        "type": "CONST",
        "value": "teachers"
       }
      ]
     },
     "getSubjectsState": {
      "type": "GET",
      "path": [
       {
        "type": "CONST",
        "value": "subjects"
       }
      ]
     }
    }
   }
  }
 },
 "/home/vlad/facultate/licenta/app/src/views/general/producers/initState.ts": {
  "biBSvhQeabuelKO": {
   "type": "producer",
   "meta": {
    "name": "initState",
    "location": {
     "start": {
      "line": 3,
      "column": 13
     },
     "end": {
      "line": 31,
      "column": 1
     }
    },
    "absoluteFilePath": "/home/vlad/facultate/licenta/app/src/views/general/producers/initState.ts",
    "absoluteRootPath": "/home/vlad/facultate/licenta/app",
    "relativeFilePath": "src/views/general/producers/initState.ts"
   },
   "sourceId": "/home/vlad/facultate/licenta/app/src/views/general/producers/initState.ts:initState",
   "buildId": "biBSvhQeabuelKO",
   "params": {
    "type": "STRUCT",
    "value": {
     "updateMessages": {
      "type": "UPDATE",
      "path": [
       {
        "type": "CONST",
        "value": "messages"
       },
       {
        "type": "CONST",
        "value": "content"
       }
      ]
     },
     "updateIsStateInitiated": {
      "type": "UPDATE",
      "path": [
       {
        "type": "CONST",
        "value": "messages"
       },
       {
        "type": "CONST",
        "value": "isStateInitiated"
       }
      ]
     }
    }
   }
  }
 },
 "/home/vlad/facultate/licenta/app/src/views/catalogue/producers/initState.ts": {
  "IXjnmYUGFYVmbCN": {
   "type": "producer",
   "meta": {
    "name": "initState",
    "location": {
     "start": {
      "line": 3,
      "column": 13
     },
     "end": {
      "line": 69,
      "column": 1
     }
    },
    "absoluteFilePath": "/home/vlad/facultate/licenta/app/src/views/catalogue/producers/initState.ts",
    "absoluteRootPath": "/home/vlad/facultate/licenta/app",
    "relativeFilePath": "src/views/catalogue/producers/initState.ts"
   },
   "sourceId": "/home/vlad/facultate/licenta/app/src/views/catalogue/producers/initState.ts:initState",
   "buildId": "IXjnmYUGFYVmbCN",
   "params": {
    "type": "STRUCT",
    "value": {
     "updateCatalogue": {
      "type": "UPDATE",
      "path": [
       {
        "type": "CONST",
        "value": "catalogue"
       },
       {
        "type": "CONST",
        "value": "catalogue"
       }
      ]
     },
     "updateIsStateInitiated": {
      "type": "UPDATE",
      "path": [
       {
        "type": "CONST",
        "value": "messages"
       },
       {
        "type": "CONST",
        "value": "isStateInitiated"
       }
      ]
     },
     "user": {
      "type": "OBSERVE",
      "path": [
       {
        "type": "CONST",
        "value": "user"
       }
      ]
     },
     "catalogueClass": {
      "type": "OBSERVE",
      "path": [
       {
        "type": "CONST",
        "value": "catalogue"
       },
       {
        "type": "CONST",
        "value": "class"
       }
      ]
     },
     "getCatalogueTeacher": {
      "type": "GET",
      "path": [
       {
        "type": "CONST",
        "value": "catalogue"
       },
       {
        "type": "CONST",
        "value": "teacher"
       }
      ]
     },
     "getCatalogueStudent": {
      "type": "GET",
      "path": [
       {
        "type": "CONST",
        "value": "catalogue"
       },
       {
        "type": "CONST",
        "value": "student"
       }
      ]
     }
    }
   }
  }
 },
 "/home/vlad/facultate/licenta/app/src/views/requests/producers/modalSaved.ts": {
  "Kr_XGOFZwSYDPCH": {
   "type": "producer",
   "meta": {
    "name": "modalSaved",
    "location": {
     "start": {
      "line": 4,
      "column": 13
     },
     "end": {
      "line": 213,
      "column": 1
     }
    },
    "absoluteFilePath": "/home/vlad/facultate/licenta/app/src/views/requests/producers/modalSaved.ts",
    "absoluteRootPath": "/home/vlad/facultate/licenta/app",
    "relativeFilePath": "src/views/requests/producers/modalSaved.ts"
   },
   "sourceId": "/home/vlad/facultate/licenta/app/src/views/requests/producers/modalSaved.ts:modalSaved",
   "buildId": "Kr_XGOFZwSYDPCH",
   "params": {
    "type": "STRUCT",
    "value": {
     "isModalSavePressed": {
      "type": "OBSERVE",
      "path": [
       {
        "type": "CONST",
        "value": "modal"
       },
       {
        "type": "CONST",
        "value": "isSavePressed"
       }
      ]
     },
     "updateIsModalSavePressed": {
      "type": "UPDATE",
      "path": [
       {
        "type": "CONST",
        "value": "modal"
       },
       {
        "type": "CONST",
        "value": "isSavePressed"
       }
      ]
     },
     "getModalFormData": {
      "type": "GET",
      "path": [
       {
        "type": "CONST",
        "value": "modal"
       },
       {
        "type": "CONST",
        "value": "formData"
       }
      ]
     },
     "getStudents": {
      "type": "GET",
      "path": [
       {
        "type": "CONST",
        "value": "students"
       }
      ]
     },
     "getUsers": {
      "type": "GET",
      "path": [
       {
        "type": "CONST",
        "value": "users"
       }
      ]
     },
     "getClasses": {
      "type": "GET",
      "path": [
       {
        "type": "CONST",
        "value": "classes"
       }
      ]
     },
     "getParents": {
      "type": "GET",
      "path": [
       {
        "type": "CONST",
        "value": "parents"
       }
      ]
     },
     "getSubjects": {
      "type": "GET",
      "path": [
       {
        "type": "CONST",
        "value": "subjects"
       }
      ]
     },
     "requests": {
      "type": "OBSERVE",
      "path": [
       {
        "type": "CONST",
        "value": "requests"
       },
       {
        "type": "CONST",
        "value": "content"
       }
      ]
     },
     "updateRequests": {
      "type": "UPDATE",
      "path": [
       {
        "type": "CONST",
        "value": "requests"
       },
       {
        "type": "CONST",
        "value": "content"
       }
      ]
     },
     "user": {
      "type": "OBSERVE",
      "path": [
       {
        "type": "CONST",
        "value": "user"
       }
      ]
     }
    }
   }
  }
 },
 "/home/vlad/facultate/licenta/app/src/views/requests/producers/initState.ts": {
  "ktaoKSQfFjuVtur": {
   "type": "producer",
   "meta": {
    "name": "initState",
    "location": {
     "start": {
      "line": 3,
      "column": 13
     },
     "end": {
      "line": 45,
      "column": 1
     }
    },
    "absoluteFilePath": "/home/vlad/facultate/licenta/app/src/views/requests/producers/initState.ts",
    "absoluteRootPath": "/home/vlad/facultate/licenta/app",
    "relativeFilePath": "src/views/requests/producers/initState.ts"
   },
   "sourceId": "/home/vlad/facultate/licenta/app/src/views/requests/producers/initState.ts:initState",
   "buildId": "ktaoKSQfFjuVtur",
   "params": {
    "type": "STRUCT",
    "value": {
     "updateRequests": {
      "type": "UPDATE",
      "path": [
       {
        "type": "CONST",
        "value": "requests"
       },
       {
        "type": "CONST",
        "value": "content"
       }
      ]
     },
     "updateIsStateInitiated": {
      "type": "UPDATE",
      "path": [
       {
        "type": "CONST",
        "value": "requests"
       },
       {
        "type": "CONST",
        "value": "isStateInitiated"
       }
      ]
     },
     "user": {
      "type": "OBSERVE",
      "path": [
       {
        "type": "CONST",
        "value": "user"
       }
      ]
     }
    }
   }
  }
 },
 "/home/vlad/facultate/licenta/app/src/components/form/modalForm.tsx": {
  "HBipqMlcdsZKjPl": {
   "type": "view",
   "meta": {
    "name": "ModalForm",
    "location": {
     "start": {
      "line": 5,
      "column": 13
     },
     "end": {
      "line": 61,
      "column": 1
     }
    },
    "absoluteFilePath": "/home/vlad/facultate/licenta/app/src/components/form/modalForm.tsx",
    "absoluteRootPath": "/home/vlad/facultate/licenta/app",
    "relativeFilePath": "src/components/form/modalForm.tsx"
   },
   "sourceId": "/home/vlad/facultate/licenta/app/src/components/form/modalForm.tsx:ModalForm",
   "buildId": "HBipqMlcdsZKjPl",
   "params": {
    "type": "STRUCT",
    "value": {
     "fields": {
      "type": "VALUE",
      "value": {
       "type": "EXTERNAL",
       "path": [
        "fields"
       ]
      }
     },
     "type": {
      "type": "VALUE",
      "value": {
       "type": "EXTERNAL",
       "path": [
        "type"
       ]
      }
     },
     "updateModalFormData": {
      "type": "UPDATE",
      "path": [
       {
        "type": "CONST",
        "value": "modal"
       },
       {
        "type": "CONST",
        "value": "formData"
       }
      ]
     },
     "modalFormData": {
      "type": "OBSERVE",
      "path": [
       {
        "type": "CONST",
        "value": "modal"
       },
       {
        "type": "CONST",
        "value": "formData"
       }
      ]
     },
     "isModalOpen": {
      "type": "OBSERVE",
      "path": [
       {
        "type": "CONST",
        "value": "modal"
       },
       {
        "type": "CONST",
        "value": "isOpen"
       }
      ]
     }
    }
   }
  }
 }
}